auth0_ai_langchain/FGARetriever.py
auth0_ai_langchain/__init__.py
auth0_ai_langchain/async_authorization/__init__.py
auth0_ai_langchain/async_authorization/async_authorizer.py
auth0_ai_langchain/async_authorization/graph_resumer.py
auth0_ai_langchain/auth0_ai.py
auth0_ai_langchain/fga/__init__.py
auth0_ai_langchain/token_vault/__init__.py
auth0_ai_langchain/token_vault/token_vault_authorizer.py
auth0_ai_langchain/utils/interrupt.py
auth0_ai_langchain/utils/tool_wrapper.py
auth0_ai_langchain-1.0.1.dist-info/LICENSE
auth0_ai_langchain-1.0.1.dist-info/METADATA
auth0_ai_langchain-1.0.1.dist-info/WHEEL
auth0_ai_langchain-1.0.1.dist-info/RECORD
