Metadata-Version: 2.3
Name: auth0-ai-langchain
Version: 1.0.1
Summary: This package is an SDK for building secure AI-powered applications using Auth0, Okta FGA and LangChain.
License: Apache-2.0
Author: Auth0
Author-email: support@auth0.com
Requires-Python: >=3.11,<4.0
Classifier: License :: OSI Approved :: Apache Software License
Classifier: Programming Language :: Python :: 3
Classifier: Programming Language :: Python :: 3.11
Classifier: Programming Language :: Python :: 3.12
Classifier: Programming Language :: Python :: 3.13
Requires-Dist: auth0-ai (>=1.0.2,<2.0.0)
Requires-Dist: langchain (>=0.3.26,<0.4.0)
Requires-Dist: langchain-core (>=0.3.69,<0.4.0)
Requires-Dist: langgraph (>=0.5.3,<0.6.0)
Requires-Dist: langgraph-sdk (>=0.1.73,<0.2.0)
Requires-Dist: openfga-sdk (>=0.9.5,<0.10.0)
Project-URL: Homepage, https://auth0.com
